afroz_bitcoin_m/__init__.py
afroz_bitcoin_m/bitcoin_price_notification.py
afroz_bitcoin_price-1.1.6.dist-info/LICENSE
afroz_bitcoin_price-1.1.6.dist-info/METADATA
afroz_bitcoin_price-1.1.6.dist-info/WHEEL
afroz_bitcoin_price-1.1.6.dist-info/entry_points.txt
afroz_bitcoin_price-1.1.6.dist-info/top_level.txt
afroz_bitcoin_price-1.1.6.dist-info/RECORD
