Metadata-Version: 2.1
Name: afroz-bitcoin-price
Version: 1.1.6
Summary: BITCOIN PRICE NOTIFICATION
Home-page: https://github.com/md-afroz-vst-au4/bitcoin_project
Author: MOHD AFROZ
Author-email: afrozjmi102@gmail.com
License: MIT
Platform: UNKNOWN
Classifier: License :: OSI Approved :: MIT License
Classifier: Programming Language :: Python :: 3
Classifier: Programming Language :: Python :: 3.7
Requires-Dist: requests
Requires-Dist: datetime
